currenapp/__init__.py
currenapp/__main__.py
currenapp/main.py
currenapp/tools.py
currenapp/ui.py
currenapp-1.0.0.dist-info/entry_points.txt
currenapp-1.0.0.dist-info/LICENSE.md
currenapp-1.0.0.dist-info/WHEEL
currenapp-1.0.0.dist-info/METADATA
currenapp-1.0.0.dist-info/RECORD
