Metadata-Version: 2.1
Name: currenapp
Version: 1.0.0
Summary: A CLI to convert different currencies.
Author: caio
Author-email: caio.2004vb@gmail.com
Requires-Python: >=3.10,<4.0
Classifier: Programming Language :: Python :: 3
Classifier: Programming Language :: Python :: 3.10
Requires-Dist: requests (>=2.28.1,<3.0.0)
Requires-Dist: typer[all] (>=0.6.1,<0.7.0)
